object_position_calculator/CoordinateCalculator.py
object_position_calculator/__init__.py
object_position_calculator/best.pt
object_position_calculator/calculate.py
object_position_calculator/detect_object.py
object_position_calculator/newCalculator.py
object_position_calculator/object_position.py
object_position_calculator/position_calculator.py
coordinate_estimate-0.1.4.dist-info/LICENSE
coordinate_estimate-0.1.4.dist-info/METADATA
coordinate_estimate-0.1.4.dist-info/WHEEL
coordinate_estimate-0.1.4.dist-info/top_level.txt
coordinate_estimate-0.1.4.dist-info/RECORD
