Metadata-Version: 2.1
Name: coordinate-estimate
Version: 0.1.4
Summary: A Python library to calculate GPS coordinates from detected points in images.
Author: ittipat jitrada
Author-email: Ittipat jitrada <ittipatjitrada@gmail.com>
License: COSI
Project-URL: Homepage, https://github.com/ITPATJIDR/Coordinate_Calculator
License-File: LICENSE
